qnorm/__init__.py
qnorm/cli.py
qnorm/quantile_normalize.py
qnorm/util.py
qnorm-0.9.0.dist-info/licenses/LICENSE
qnorm-0.9.0.dist-info/METADATA
qnorm-0.9.0.dist-info/WHEEL
qnorm-0.9.0.dist-info/entry_points.txt
qnorm-0.9.0.dist-info/top_level.txt
qnorm-0.9.0.dist-info/RECORD
