Metadata-Version: 2.4
Name: qnorm
Version: 0.9.0
Summary: Quantile normalization
Author-email: Maarten van der Sande <maartenvandersande@hotmail.com>
Maintainer-email: Maarten van der Sande <maartenvandersande@hotmail.com>
License: MIT License
Project-URL: Homepage, https://github.com/Maarten-vd-Sande/qnorm
Project-URL: Repository, https://github.com/Maarten-vd-Sande/qnorm
Project-URL: Issues, https://github.com/Maarten-vd-Sande/qnorm/issues
Keywords: quantile,normalization,bioinformatics
Classifier: Development Status :: 1 - Planning
Classifier: Intended Audience :: Developers
Classifier: Intended Audience :: Science/Research
Classifier: License :: OSI Approved :: MIT License
Classifier: Operating System :: POSIX :: Linux
Classifier: Operating System :: MacOS :: MacOS X
Classifier: Programming Language :: Python
Classifier: Programming Language :: Python :: 3
Classifier: Programming Language :: Python :: 3.7
Classifier: Programming Language :: Python :: 3.8
Classifier: Programming Language :: Python :: 3.9
Classifier: Programming Language :: Python :: 3.10
Classifier: Programming Language :: Python :: 3.11
Classifier: Programming Language :: Python :: 3.12
Classifier: Topic :: Scientific/Engineering :: Bio-Informatics
Requires-Python: >=3.7
License-File: LICENSE
Requires-Dist: numba
Requires-Dist: numpy
Dynamic: license-file
